omniblack/path/__init__.py
omniblack/path/file_locking.py
omniblack/path/path.py
omniblack.path-0.1.5.dist-info/LICENSE.txt
omniblack.path-0.1.5.dist-info/WHEEL
omniblack.path-0.1.5.dist-info/METADATA
omniblack.path-0.1.5.dist-info/RECORD
