Metadata-Version: 2.1
Name: omniblack.path
Version: 0.1.5
Summary: A tool to get files based on the XDG Base Directory Specification.
License: AGPL-3.0-or-later
Author: Terry Patterson
Author-email: Terryp@wegrok.net
Requires-Python: >=3.9,<4.0
Classifier: License :: OSI Approved :: GNU Affero General Public License v3 or later (AGPLv3+)
Classifier: Programming Language :: Python :: 3
Requires-Dist: more-itertools (>=8.6.0,<9.0.0)
Requires-Dist: ruamel.yaml (>=0.16.12,<0.17.0)
